zisan/__init__.py
zisan/FileTools/__init__.py
zisan/FileTools/tools.py
zisan/Filter_effects/__init__.py
zisan/Filter_effects/color_enhanced.py
zisan/ObjDetect/Interface.py
zisan/ObjDetect/__init__.py
zisan/ObjDetect/models.py
zisan/ObjDetect/test.py
zisan/ObjDetect/utils/__init__.py
zisan/ObjDetect/utils/adabound.py
zisan/ObjDetect/utils/datasets.py
zisan/ObjDetect/utils/google_utils.py
zisan/ObjDetect/utils/parse_config.py
zisan/ObjDetect/utils/torch_utils.py
zisan/ObjDetect/utils/utils.py
zisan/Seg/Interface.py
zisan/Seg/__init__.py
zisan/Seg/interaction_net.py
zisan/Seg/model.py
zisan/Seg/utils.py
zisan/Seg/davisinteractive/__init__.py
zisan/Seg/davisinteractive/common.py
zisan/Seg/davisinteractive/logging.py
zisan/Seg/davisinteractive/logging_test.py
zisan/Seg/davisinteractive/metrics/__init__.py
zisan/Seg/davisinteractive/metrics/jaccard.py
zisan/Seg/davisinteractive/metrics/jaccard_test.py
zisan/Seg/davisinteractive/robot/__init__.py
zisan/Seg/davisinteractive/robot/interactive_robot.py
zisan/Seg/davisinteractive/robot/interactive_robot_test.py
zisan/Seg/davisinteractive/session/__init__.py
zisan/Seg/davisinteractive/session/session.py
zisan/Seg/davisinteractive/session/session_test.py
zisan/Seg/davisinteractive/storage/__init__.py
zisan/Seg/davisinteractive/storage/abstract.py
zisan/Seg/davisinteractive/storage/local.py
zisan/Seg/davisinteractive/storage/local_test.py
zisan/Seg/davisinteractive/third_party/__init__.py
zisan/Seg/davisinteractive/third_party/mask_api/__init__.py
zisan/Seg/davisinteractive/third_party/mask_api/mask.py
zisan/Seg/davisinteractive/third_party/mask_api/mask_test.py
zisan/Seg/davisinteractive/utils/__init__.py
zisan/Seg/davisinteractive/utils/mask.py
zisan/Seg/davisinteractive/utils/mask_test.py
zisan/Seg/davisinteractive/utils/operations.py
zisan/Seg/davisinteractive/utils/scribbles.py
zisan/Seg/davisinteractive/utils/scribbles_test.py
zisan/Seg/davisinteractive/utils/visualization.py
zisan-1.0.21.dist-info/METADATA
zisan-1.0.21.dist-info/WHEEL
zisan-1.0.21.dist-info/top_level.txt
zisan-1.0.21.dist-info/RECORD
