Metadata-Version: 2.1
Name: zisan
Version: 1.0.21
Summary: Integrated CV basic application development kit based on Pytorch
Home-page: http://www.jintupersonal.com/zisan/
Author: JintuZheng
Author-email: jintuzheng@outlook.com
License: MIT
Keywords: zisan instanceSegmentation Object detecttion cv
Platform: UNKNOWN
Requires-Python: >=3.5
Requires-Dist: numpy
Requires-Dist: torch
Requires-Dist: pillow
Requires-Dist: matplotlib
Requires-Dist: torchvision
Requires-Dist: opencv-python
Requires-Dist: scikit-image
Requires-Dist: scipy
